{
  "_id": "zCKTaUJBH7P2QpUw",
  "name": "Forestry",
  "type": "skill",
  "img": "icons/svg/temple.svg",
  "effects": [],
  "folder": null,
  "flags": {
    "core": {}
  },
  "system": {
    "description": "<p>Helps in navigating the wilderness, foraging, survival, finding shelter and other tasks.</p>",
    "ability": "wis",
    "subtype": "practical",
    "bonus": 0
  },
  "_stats": {
    "systemId": "helveczia",
    "systemVersion": "3.1.2",
    "coreVersion": "11.315",
    "createdTime": 1708209591012,
    "modifiedTime": 1708209691064,
    "lastModifiedBy": "G5iize41GRbYKQLE"
  },
  "sort": 0,
  "ownership": {
    "default": 0,
    "G5iize41GRbYKQLE": 3
  },
  "_key": "!items!zCKTaUJBH7P2QpUw"
}
